laboratory/__init__.py
laboratory/exceptions.py
laboratory/experiment.py
laboratory/observation.py
laboratory/result.py
laboratory-1.0.2.dist-info/LICENCE
laboratory-1.0.2.dist-info/METADATA
laboratory-1.0.2.dist-info/WHEEL
laboratory-1.0.2.dist-info/top_level.txt
laboratory-1.0.2.dist-info/RECORD
