Metadata-Version: 2.1
Name: laboratory
Version: 1.0.2
Summary: Sure-footed refactoring achieved through experimenting
Home-page: https://github.com/joealcorn/laboratory
Author: Joe Alcorn
Author-email: joealcorn123@gmail.com
License: MIT
Platform: UNKNOWN
Classifier: Development Status :: 5 - Production/Stable
Classifier: Intended Audience :: Developers
Classifier: Intended Audience :: Developers
Classifier: License :: OSI Approved :: MIT License
Classifier: Programming Language :: Python :: 2
Classifier: Programming Language :: Python :: 2.6
Classifier: Programming Language :: Python :: 2.7
Classifier: Programming Language :: Python :: 3
Classifier: Programming Language :: Python :: 3.1
Classifier: Programming Language :: Python :: 3.3
Classifier: Programming Language :: Python :: 3.4
Classifier: Programming Language :: Python :: 3.5
Classifier: Programming Language :: Python :: 3.6
Classifier: Topic :: Software Development :: Testing
Classifier: Topic :: Utilities
Provides-Extra: dev
Requires-Dist: Sphinx (==1.6.6) ; extra == 'dev'
Requires-Dist: alabaster (==0.7.12) ; extra == 'dev'
